ambition_django_uuidfield-0.5.0.dist-info/DESCRIPTION.rst
ambition_django_uuidfield-0.5.0.dist-info/METADATA
ambition_django_uuidfield-0.5.0.dist-info/metadata.json
ambition_django_uuidfield-0.5.0.dist-info/pbr.json
ambition_django_uuidfield-0.5.0.dist-info/RECORD
ambition_django_uuidfield-0.5.0.dist-info/top_level.txt
ambition_django_uuidfield-0.5.0.dist-info/WHEEL
uuidfield/__init__.py
uuidfield/fields.py
uuidfield/models.py
uuidfield/tests/__init__.py
uuidfield/tests/models.py
uuidfield/tests/tests.py
