Metadata-Version: 2.0
Name: ambition-django-uuidfield
Version: 0.5.0
Summary: Ambition fork of dcramer/django-uuidfield, UUIDField in Django
Home-page: https://github.com/ambitioninc/django-uuidfield
Author: David Cramer
Author-email: dcramer@gmail.com
License: UNKNOWN
Platform: UNKNOWN
Classifier: Framework :: Django
Classifier: Intended Audience :: Developers
Classifier: Intended Audience :: System Administrators
Classifier: Operating System :: OS Independent
Classifier: Topic :: Software Development
Requires-Dist: django
Requires-Dist: six
